resources/__init__.py
tests/__init__.py
tests/correspondence.py
tests/generateTestDatasets.py
tests/testparser.py
appel_geocode-1.1.0.dist-info/LICENSE
appel_geocode-1.1.0.dist-info/METADATA
appel_geocode-1.1.0.dist-info/WHEEL
appel_geocode-1.1.0.dist-info/top_level.txt
appel_geocode-1.1.0.dist-info/RECORD
