Metadata-Version: 2.1
Name: appel-geocode
Version: 1.1.0
Summary: A faster spatial join/reverse geocoding algorithm
Home-page: https://github.com/gcoimbra/appel
Author: Gabriel Coimbra
Author-email: gcoimbra@riseup.net
License: UNKNOWN
Platform: UNKNOWN
Classifier: Development Status :: 4 - Beta
Classifier: Programming Language :: Python :: 3
Classifier: License :: OSI Approved :: GNU Affero General Public License v3
Classifier: Operating System :: POSIX :: Linux
Requires-Python: >=3.6
Requires-Dist: matplotlib (==3.1.1)
Requires-Dist: Shapely (==1.6.4.post2)
Requires-Dist: geopandas (==0.5.1)
Requires-Dist: numpy (==1.17.2)
Requires-Dist: pandas (==0.25.1)
Requires-Dist: typing-extensions (==3.7.4)
